LICENSE
MANIFEST.in
README.rst
setup.py
chd/__init__.py
chd/__main__.py
chd/items.py
chd/middlewares.py
chd/pipelines.py
chd/settings.py
chd.egg-info/PKG-INFO
chd.egg-info/SOURCES.txt
chd.egg-info/dependency_links.txt
chd.egg-info/entry_points.txt
chd.egg-info/requires.txt
chd.egg-info/top_level.txt
chd/spiders/__init__.py
chd/spiders/ch_spider.py